{
    "0": {
        "r": 1224, 
        "u": 1122, 
        "d": 2125, 
        "l": 952
    }, 
    "2057": {
        "r": 1190, 
        "u": 1649, 
        "d": 935, 
        "l": 935
    }, 
    "1547": {
        "r": 867, 
        "u": 2142, 
        "d": 391, 
        "l": 1343
    }, 
    "1037": {
        "r": 1547, 
        "u": 357, 
        "d": 867, 
        "l": 1377
    }, 
    "527": {
        "r": 1377, 
        "u": 1428, 
        "d": 1105, 
        "l": 1479
    }, 
    "17": {
        "r": 901, 
        "u": 833, 
        "d": 1428, 
        "l": 510
    }, 
    "2074": {
        "r": 255, 
        "u": 1649, 
        "d": 1003, 
        "l": 1751
    }, 
    "1564": {
        "r": 646, 
        "u": 1224, 
        "d": 578, 
        "l": 986
    }, 
    "1054": {
        "r": 238, 
        "u": 425, 
        "d": 204, 
        "l": 1224
    }, 
    "544": {
        "r": 1751, 
        "u": 272, 
        "d": 1870, 
        "l": 2040
    }, 
    "34": {
        "r": 1564, 
        "u": 1037, 
        "d": 663, 
        "l": 1564
    }, 
    "2091": {
        "r": 1122, 
        "u": 1972, 
        "d": 1717, 
        "l": 255
    }, 
    "1581": {
        "r": 51, 
        "u": 765, 
        "d": 1938, 
        "l": 578
    }, 
    "1071": {
        "r": 748, 
        "u": 1003, 
        "d": 1326, 
        "l": 1207
    }, 
    "561": {
        "r": 34, 
        "u": 1343, 
        "d": 714, 
        "l": 867
    }, 
    "51": {
        "r": 1054, 
        "u": 2108, 
        "d": 340, 
        "l": 374
    }, 
    "2108": {
        "r": 1071, 
        "u": 1156, 
        "d": 85, 
        "l": 663
    }, 
    "1598": {
        "r": 1156, 
        "u": 170, 
        "d": 1598, 
        "l": 1547
    }, 
    "1088": {
        "r": 1870, 
        "u": 1921, 
        "d": 1513, 
        "l": 1173
    }, 
    "578": {
        "r": 1802, 
        "u": 765, 
        "d": 544, 
        "l": 391
    }, 
    "68": {
        "r": 680, 
        "u": 238, 
        "d": 901, 
        "l": 1887
    }, 
    "2125": {
        "r": 1241, 
        "u": 697, 
        "d": 1428, 
        "l": 1479
    }, 
    "1615": {
        "r": 2040, 
        "u": 1530, 
        "d": 510, 
        "l": 1003
    }, 
    "1105": {
        "r": 629, 
        "u": 442, 
        "d": 2125, 
        "l": 1938
    }, 
    "595": {
        "r": 1989, 
        "u": 952, 
        "d": 1224, 
        "l": 1445
    }, 
    "85": {
        "r": 1309, 
        "u": 595, 
        "d": 1564, 
        "l": 1054
    }, 
    "2142": {
        "r": 1734, 
        "u": 1887, 
        "d": 2074, 
        "l": 765
    }, 
    "1632": {
        "r": 952, 
        "u": 1003, 
        "d": 1122, 
        "l": 680
    }, 
    "1122": {
        "r": 1717, 
        "u": 1241, 
        "d": 1887, 
        "l": 1819
    }, 
    "612": {
        "r": 884, 
        "u": 1343, 
        "d": 1734, 
        "l": 1768
    }, 
    "2159": {
        "r": 1751, 
        "u": 1887, 
        "d": 1224, 
        "l": 595
    }, 
    "1649": {
        "r": 1326, 
        "u": 1462, 
        "d": 748, 
        "l": 136
    }, 
    "1139": {
        "r": 391, 
        "u": 1411, 
        "d": 850, 
        "l": 1224
    }, 
    "629": {
        "r": 1717, 
        "u": 2108, 
        "d": 255, 
        "l": 1377
    }, 
    "119": {
        "r": 1921, 
        "u": 170, 
        "d": 323, 
        "l": 1700
    }, 
    "1666": {
        "r": 2159, 
        "u": 901, 
        "d": 867, 
        "l": 493
    }, 
    "1156": {
        "r": 1343, 
        "u": 986, 
        "d": 1921, 
        "l": 2040
    }, 
    "646": {
        "r": 2142, 
        "u": 1547, 
        "d": 1802, 
        "l": 374
    }, 
    "136": {
        "r": 323, 
        "u": 170, 
        "d": 884, 
        "l": 578
    }, 
    "1683": {}, 
    "1173": {
        "r": 952, 
        "u": 1003, 
        "d": 374, 
        "l": 629
    }, 
    "663": {
        "r": 374, 
        "u": 1938, 
        "d": 306, 
        "l": 1173
    }, 
    "153": {
        "r": 1020, 
        "u": 0, 
        "d": 1445, 
        "l": 0
    }, 
    "1700": {
        "r": 935, 
        "u": 714, 
        "d": 1173, 
        "l": 1785
    }, 
    "1190": {
        "r": 1904, 
        "u": 85, 
        "d": 204, 
        "l": 1887
    }, 
    "680": {
        "r": 595, 
        "u": 867, 
        "d": 1751, 
        "l": 1904
    }, 
    "170": {
        "r": 748, 
        "u": 1870, 
        "d": 1445, 
        "l": 289
    }, 
    "1717": {
        "r": 1462, 
        "u": 2074, 
        "d": 629, 
        "l": 2091
    }, 
    "1207": {
        "r": 1836, 
        "u": 1632, 
        "d": 1938, 
        "l": 1904
    }, 
    "697": {
        "r": 884, 
        "u": 1343, 
        "d": 136, 
        "l": 136
    }, 
    "187": {
        "r": 1241, 
        "u": 969, 
        "d": 884, 
        "l": 1717
    }, 
    "1734": {
        "r": 2159, 
        "u": 1598, 
        "d": 374, 
        "l": 1445
    }, 
    "1224": {
        "r": 170, 
        "u": 2142, 
        "d": 952, 
        "l": 136
    }, 
    "714": {
        "r": 2074, 
        "u": 272, 
        "d": 136, 
        "l": 1717
    }, 
    "204": {
        "r": 595, 
        "u": 884, 
        "d": 1649, 
        "l": 1343
    }, 
    "1751": {
        "r": 1802, 
        "u": 1377, 
        "d": 986, 
        "l": 2125
    }, 
    "1241": {
        "r": 459, 
        "u": 2159, 
        "l": 1241, 
        "d": 306
    }, 
    "731": {
        "r": 1564, 
        "u": 799, 
        "d": 1241, 
        "l": 2125
    }, 
    "221": {
        "r": 1139, 
        "u": 374, 
        "d": 2159, 
        "l": 459
    }, 
    "1768": {
        "r": 306, 
        "u": 986, 
        "d": 1615, 
        "l": 2159
    }, 
    "1258": {
        "r": 2006, 
        "u": 85, 
        "d": 68, 
        "l": 578
    }, 
    "748": {
        "r": 1870, 
        "u": 1224, 
        "d": 85, 
        "l": 510
    }, 
    "238": {
        "r": 1054, 
        "u": 1054, 
        "d": 255, 
        "l": 510
    }, 
    "1785": {
        "r": 1190, 
        "u": 714, 
        "d": 2023, 
        "l": 1938
    }, 
    "1275": {
        "r": 850, 
        "u": 850, 
        "d": 2074, 
        "l": 17
    }, 
    "765": {
        "r": 663, 
        "u": 1938, 
        "d": 1309, 
        "l": 935
    }, 
    "255": {
        "r": 595, 
        "u": 425, 
        "d": 306, 
        "l": 1751
    }, 
    "1802": {
        "r": 884, 
        "u": 1666, 
        "d": 663, 
        "l": 714
    }, 
    "1292": {
        "r": 1751, 
        "u": 935, 
        "d": 255, 
        "l": 0
    }, 
    "782": {
        "r": 1275, 
        "u": 1972, 
        "d": 765, 
        "l": 425
    }, 
    "272": {
        "r": 272, 
        "u": 1921, 
        "d": 1173, 
        "l": 748
    }, 
    "1819": {
        "r": 493, 
        "u": 1071, 
        "d": 816, 
        "l": 1564
    }, 
    "1309": {
        "r": 595, 
        "u": 1309, 
        "d": 2040, 
        "l": 510
    }, 
    "799": {
        "r": 561, 
        "u": 884, 
        "d": 952, 
        "l": 1836
    }, 
    "289": {
        "r": 935, 
        "u": 1938, 
        "d": 2159, 
        "l": 1258
    }, 
    "1836": {
        "r": 1734, 
        "u": 765, 
        "d": 2091, 
        "l": 1224
    }, 
    "1326": {
        "r": 2074, 
        "u": 1972, 
        "d": 1972, 
        "l": 578
    }, 
    "816": {
        "r": 493, 
        "u": 1564, 
        "d": 425, 
        "l": 1445
    }, 
    "306": {
        "r": 1564, 
        "u": 136, 
        "d": 765, 
        "l": 765
    }, 
    "1343": {
        "r": 1649, 
        "u": 816, 
        "d": 2074, 
        "l": 1870
    }, 
    "833": {
        "r": 306, 
        "u": 952, 
        "d": 952, 
        "l": 1360
    }, 
    "323": {
        "r": 1173, 
        "u": 544, 
        "d": 2125, 
        "l": 765
    }, 
    "1870": {
        "r": 204, 
        "u": 1921, 
        "d": 1904, 
        "l": 680
    }, 
    "1360": {
        "r": 1717, 
        "u": 1241, 
        "d": 272, 
        "l": 527
    }, 
    "850": {
        "r": 1887, 
        "u": 884, 
        "d": 1445, 
        "l": 1479
    }, 
    "340": {
        "r": 374, 
        "u": 1649, 
        "d": 221, 
        "l": 714
    }, 
    "1887": {
        "r": 85, 
        "u": 1496, 
        "d": 578, 
        "l": 2108
    }, 
    "1377": {
        "r": 850, 
        "u": 391, 
        "d": 1989, 
        "l": 1751
    }, 
    "867": {
        "r": 1190, 
        "u": 204, 
        "d": 1190, 
        "l": 1292
    }, 
    "357": {
        "r": 459, 
        "u": 374, 
        "d": 187, 
        "l": 510
    }, 
    "1904": {
        "r": 884, 
        "u": 1938, 
        "d": 1819, 
        "l": 680
    }, 
    "1394": {
        "r": 1377, 
        "u": 1955, 
        "d": 1377, 
        "l": 986
    }, 
    "884": {
        "r": 2108, 
        "u": 2108, 
        "d": 1462, 
        "l": 952
    }, 
    "374": {
        "r": 1173, 
        "u": 1122, 
        "d": 1887, 
        "l": 629
    }, 
    "1921": {
        "r": 1479, 
        "u": 2040, 
        "d": 1938, 
        "l": 2159
    }, 
    "1411": {
        "r": 1343, 
        "u": 2125, 
        "d": 272, 
        "l": 1088
    }, 
    "901": {
        "r": 2091, 
        "u": 1224, 
        "d": 1428, 
        "l": 2159
    }, 
    "391": {
        "r": 1071, 
        "u": 765, 
        "d": 2142, 
        "l": 850
    }, 
    "1938": {
        "r": 714, 
        "u": 629, 
        "d": 935, 
        "l": 2057
    }, 
    "1428": {
        "r": 1054, 
        "u": 374, 
        "d": 663, 
        "l": 493
    }, 
    "918": {
        "r": 612, 
        "u": 1241, 
        "d": 1326, 
        "l": 1564
    }, 
    "408": {
        "r": 697, 
        "u": 1224, 
        "d": 1887, 
        "l": 1377
    }, 
    "1955": {
        "r": 323, 
        "u": 680, 
        "d": 918, 
        "l": 1547
    }, 
    "1445": {
        "r": 952, 
        "u": 408, 
        "d": 646, 
        "l": 1921
    }, 
    "935": {
        "r": 935, 
        "u": 986, 
        "d": 1173, 
        "l": 748
    }, 
    "425": {
        "r": 663, 
        "u": 374, 
        "d": 1445, 
        "l": 986
    }, 
    "1972": {
        "r": 1904, 
        "u": 714, 
        "d": 901, 
        "l": 1632
    }, 
    "1462": {
        "r": 1972, 
        "u": 952, 
        "d": 1938, 
        "l": 391
    }, 
    "952": {
        "r": 204, 
        "u": 544, 
        "d": 255, 
        "l": 306
    }, 
    "442": {
        "r": 986, 
        "u": 1343, 
        "d": 238, 
        "l": 476
    }, 
    "1989": {
        "r": 1343, 
        "u": 1921, 
        "d": 425, 
        "l": 544
    }, 
    "1479": {
        "r": 1802, 
        "u": 323, 
        "d": 1938, 
        "l": 323
    }, 
    "969": {
        "r": 1309, 
        "u": 170, 
        "d": 1683
    }, 
    "459": {
        "r": 1003, 
        "u": 1309, 
        "l": 459, 
        "d": 884
    }, 
    "2006": {
        "r": 1581, 
        "u": 2142, 
        "d": 578, 
        "l": 323
    }, 
    "1496": {
        "r": 1802, 
        "u": 680, 
        "d": 1717, 
        "l": 170
    }, 
    "986": {
        "r": 323, 
        "u": 850, 
        "d": 204, 
        "l": 1173
    }, 
    "476": {
        "r": 1632, 
        "u": 697, 
        "d": 1428, 
        "l": 119
    }, 
    "2023": {
        "r": 1666, 
        "u": 153, 
        "d": 1428, 
        "l": 935
    }, 
    "1513": {
        "r": 1479, 
        "u": 170, 
        "d": 204, 
        "l": 782
    }, 
    "1003": {
        "r": 867, 
        "u": 1666, 
        "d": 935, 
        "l": 629
    }, 
    "493": {
        "r": 816, 
        "u": 1564, 
        "d": 867, 
        "l": 1377
    }, 
    "2040": {
        "r": 1445, 
        "u": 1462, 
        "d": 1564, 
        "l": 2125
    }, 
    "1530": {
        "r": 1972, 
        "u": 2091, 
        "d": 850, 
        "l": 731
    }, 
    "1020": {
        "r": 1003, 
        "u": 1394, 
        "d": 544, 
        "l": 901
    }, 
    "510": {
        "r": 1003, 
        "u": 136, 
        "d": 459, 
        "l": 204
    }
}